{"updated": "2026-06-09T01:56:50Z", "source": "eastmoney-news", "data": [{"time": "2026-06-09 09:53:40", "title": "AI革命已成市场共识，人工智能ETF易方达(159819)上涨2.13%，政策部署数据赋能人工智能发展", "summary": "【AI革命已成市场共识，人工智能ETF易方达(159819)上涨2.13%，政策部署数据赋能人工智能发展】截至2026年6月9日09:40，中证人工智能主题指数(930713)强势上涨2.03%，人工智能ETF易方达(159819)上涨2.13%，成交1.13亿元。", "stocks": "90.BK0800, 150.012322"}, {"time": "2026-06-09 09:51:57", "title": "财政部、商务部修订印发《服务业发展资金管理办法》", "summary": "【财政部、商务部修订印发《服务业发展资金管理办法》】为加强服务业发展资金管理，充分发挥中央财政资金在引导促进服务业加快发展方面的作用，财政部、商务部修订了《服务业发展资金管理办法》，现予印发。", "stocks": "1007.BK000390"}, {"time": "2026-06-09 09:51:26", "title": "存储芯片概念表现活跃 金太阳涨超12%", "summary": "存储芯片概念表现活跃，金太阳涨超12%，德明利、江波龙、大为股份、神工股份、普冉股份跟涨。", "stocks": "90.BK1137, 999.177788"}, {"time": "2026-06-09 09:51:12", "title": "科创芯片ETF易方达（589130）涨近3%，半导体产业链景气持续扩散", "summary": "【科创芯片ETF易方达（589130）涨近3%，半导体产业链景气持续扩散】截至2026年6月9日9时46分，科创芯片ETF易方达（589130）开盘后震荡上行，现涨2.84%，成交额达2235万元，市场交投活跃。该ETF跟踪的上证科创板芯片指数汇集了科创板芯片设计、制造、封测等各环节核心标的，受益于半导体行业景气度持续上行及国产替代逻辑强化。", "stocks": "90.BK1036, 90.BK0459"}, {"time": "2026-06-09 09:50:43", "title": "半导体板块持续走强 杰华特触及20cm涨停", "summary": "半导体板块持续走强，杰华特触及20cm涨停，晶丰明源、富创精密、宏微科技、星宸科技、沪硅产业、东芯股份等跟涨。", "stocks": "90.BK1036, 90.BK0459"}, {"time": "2026-06-09 09:50:43", "title": "李家超：将于6月15日展开香港五年规划公众咨询", "summary": "【李家超：将于6月15日展开香港五年规划公众咨询】香港特区行政长官李家超今日（9日）宣布，特区政府将于6月15日展开香港五年规划公众咨询。", "stocks": ""}, {"time": "2026-06-09 09:49:02", "title": "机器人概念反复活跃 埃斯顿2连板", "summary": "机器人概念反复活跃，埃斯顿2连板，晋拓股份涨停，景业智能、腾亚精工、丰光精密涨超10%，豪恩汽电、中科三环、秦川机床、征和工业等涨幅靠前。", "stocks": ""}, {"time": "2026-06-09 09:48:43", "title": "美副总统：美以在推动与伊朗达成核问题协议上可能存在利益分歧", "summary": "【美副总统：美以在推动与伊朗达成核问题协议上可能存在利益分歧】当地时间6月8日，美国副总统万斯表示，美国在推动与伊朗达成核协议问题上的利益可能与以色列存在差异，但特朗普政府仍将继续推进谈判。万斯当天接受采访时表示，总统特朗普相信，美方有机会达成一项长期解决伊朗核问题的协议。“以色列可能喜欢这项协议，也可能不喜欢，但归根结底，我们认为这符合美利坚合众国的最佳利益。”", "stocks": ""}, {"time": "2026-06-09 09:48:09", "title": "美股芯片全面反弹，芯片ETF东财早盘高开超2.5%", "summary": "【美股芯片全面反弹，芯片ETF东财早盘高开超2.5%】受美国与日韩半导体情绪全面刺激，芯片ETF东财(159599)6月9日早盘高开超2.5%，展现出回调后的强劲拉升之势。", "stocks": "150.013446, 150.159813"}, {"time": "2026-06-09 09:47:08", "title": "新华网科普丨量子纠缠如何催生全新技术革命", "summary": "【新华网科普丨量子纠缠如何催生全新技术革命】量子纠缠是量子力学的核心现象，既是当前量子通信、量子计算等前沿科技的底层基础，也是大众最感兴趣却最易误解的量子概念。它究竟是粒子的“隔空约定”，还是千里之外的“心有灵犀”？国家级人才、国家重点研发计划首席科学家、北京航空航天大学教授周苗为我们解锁量子科技的奥秘。", "stocks": "90.BK0710, 150.012372"}, {"time": "2026-06-09 09:44:47", "title": "三峡水库提前完成年度消落任务", "summary": "【三峡水库提前完成年度消落任务】记者从水利部长江水利委员会了解到，近日，三峡水库水位消落至147.78米，提前完成消落任务。三峡水库本轮消落自2025年10月下旬开始，共消落水位约27米，腾出防洪库容约208亿立方米。", "stocks": ""}, {"time": "2026-06-09 09:44:43", "title": "房地产板块持续走低 南山控股、华丽家族逼近跌停", "summary": "房地产板块持续走低，南山控股、华丽家族逼近跌停，荣安地产跌超9%，荣丰控股、大悦城、光大嘉宝纷纷下挫。", "stocks": "90.BK0451, 0.002314"}, {"time": "2026-06-09 09:43:38", "title": "徐工集团等成立新能源公司 含AI业务", "summary": "【徐工集团等成立新能源公司 含AI业务】企查查APP显示，近日，徐州徐工力高新能源有限公司成立，注册资本5000万元，经营范围包含：智能控制系统集成；汽车零部件研发；新能源汽车电附件销售；人工智能应用软件开发等。企查查股权穿透显示，该公司由徐州工程机械集团有限公司全资子公司徐工集团产业投资发展（徐州）有限公司等共同持股。", "stocks": "150.515980, 0.161631"}, {"time": "2026-06-09 09:42:14", "title": "煤炭板块震荡下挫 郑州煤电逼近跌停", "summary": "煤炭板块震荡下挫，郑州煤电逼近跌停，安泰集团、大有能源、陕西黑猫、宝泰隆跌幅居前。", "stocks": "90.BK0437, 1.600121"}, {"time": "2026-06-09 09:41:18", "title": "半导体设备股盘初活跃 亚翔集成2连板", "summary": "半导体设备股活跃，洁净室方向领涨，亚翔集成2连板，圣晖集成逼近涨停，富创精密、华康洁净、柏诚股份、中微公司、美埃科技跟涨。", "stocks": "90.BK1326, 90.BK0816"}], "count": 15}
