{"updated": "2026-07-01T16:16:01Z", "source": "eastmoney-news", "data": [{"time": "2026-07-02 00:06:49", "title": "据俄罗斯经济部 俄罗斯5月份GDP同比增长0.3%", "summary": "据俄罗斯经济部，俄罗斯5月份GDP同比增长0.3%。", "stocks": ""}, {"time": "2026-07-02 00:06:16", "title": "布伦特原油期货日内大跌超3%", "summary": "【布伦特原油期货日内大跌超3%】布伦特原油期货日内大跌超3%，现报71.1美元/桶。", "stocks": "90.BK1361"}, {"time": "2026-07-02 00:03:12", "title": "特斯拉在意大利的新车注册量在6月份同比增长42.78%", "summary": "【特斯拉在意大利的新车注册量在6月份同比增长42.78%】特斯拉在意大利的新车注册量在6月份同比增长42.78%，1月至6月新车注册量同比增长22.42%。", "stocks": "90.BK0644, 105.TSLA"}, {"time": "2026-07-02 00:01:43", "title": "亚马逊2025年碳排放量因数据中心激增上升16%", "summary": "亚马逊2025年碳排放量因数据中心激增上升16%。", "stocks": "90.BK0922, 105.AMZN"}, {"time": "2026-07-01 23:58:12", "title": "乐创技术：取得1项发明专利证书", "summary": "【乐创技术：取得1项发明专利证书】乐创技术公告，公司近日收到国家知识产权局颁发的1项发明专利证书，发明名称为五轴点胶系统的伺服参数调整方法及系统、设备、介质。", "stocks": "0.920425"}, {"time": "2026-07-01 23:57:44", "title": "宏海科技：获485万元政府补贴", "summary": "【宏海科技：获485万元政府补贴】宏海科技公告，2026年6月30日公司收到与收益相关的政府补助资金485万元，占公司最近一个会计年度经审计净利润的26.35%。", "stocks": "0.920108"}, {"time": "2026-07-01 23:57:36", "title": "梓橦宫：取得1项实用新型专利证书", "summary": "【梓橦宫：取得1项实用新型专利证书】梓橦宫公告，近日公司取得国家知识产权局颁发的1项实用新型专利证书，专利名称为一种带药材定位结构的中药切片机。", "stocks": "0.920566"}, {"time": "2026-07-01 23:57:08", "title": "建邦科技：取得1项发明专利证书", "summary": "【建邦科技：取得1项发明专利证书】建邦科技公告，2026年6月30日收到国家知识产权局颁发的1项发明专利证书，发明名称为一种后加装拖车同步制动方法和装置。", "stocks": "0.920242"}, {"time": "2026-07-01 23:56:45", "title": "奥美森：拟回购41.5万-83万股", "summary": "【奥美森：拟回购41.5万-83万股】奥美森公告，公司拟以集中竞价方式回购A股股份41.5万至83万股（含），回购价格上限30元/股；资金来源为自有资金及兴业银行中山分行提供的股票回购专项贷款（专项贷款不超回购资金90%）；本次回购股份将用于实施员工持股计划或股权激励。", "stocks": "999.457369, 0.920080"}, {"time": "2026-07-01 23:54:48", "title": "丹娜生物：取得体外诊断试剂注册证", "summary": "【丹娜生物：取得体外诊断试剂注册证】丹娜生物公告，公司新品曲霉、新型隐球菌及耶氏肺孢子菌核酸检测试剂盒（荧光PCR法）获国家药监局颁发的第三类体外诊断试剂注册证。", "stocks": "90.BK1603, 90.BK0841"}, {"time": "2026-07-01 23:54:26", "title": "华密新材：2026年二季度获3项专利", "summary": "【华密新材：2026年二季度获3项专利】华密新材公告，2026年第二季度公司共取得3项国家知识产权局颁发的专利证书，包含2项发明专利、1项实用新型专利，另有1项前期购买的发明专利于期内完成权属变更至公司名下。", "stocks": "0.920247"}, {"time": "2026-07-01 23:43:49", "title": "联合国秘书长呼吁各国加强人工智能治理", "summary": "【联合国秘书长呼吁各国加强人工智能治理】当地时间7月1日，联合国秘书长古特雷斯在纽约联合国总部表示，人工智能在缺乏共同规则的情况下发展得越快，各国政府和人民对其发展结果所能发挥的影响就越小。他呼吁各国政府不要等待，应加强人工智能治理。", "stocks": ""}, {"time": "2026-07-01 23:40:10", "title": "水井坊回复上交所年报问询函：公司收入及利润变动趋势与行业整体保持一致 不存在偏离行业的异常情形", "summary": "【水井坊回复上交所年报问询函：公司收入及利润变动趋势与行业整体保持一致 不存在偏离行业的异常情形】水井坊(600779.SH)公告称，公司回复上交所关于2025年年报的信息披露监管问询函。2025年公司营业收入下降主要系受市场竞争环境变化影响，白酒销量下降以及吨酒单价下降所致；公司成品酒营业收入同比减少21.67亿元，其中核心品臻酿系列，销量减少2,665吨，营业收入减少16.12亿元，井台系列销量减少269吨，营业收入减少3.63亿元，其他非成品酒类营业收入减少0.12亿元，合计导致公司本年度营业收入减少21.79亿元。公司定价采用以品牌价值与历史文化稀缺性为主、参考主要竞品同价位带定价、兼顾成本与渠道合理利润的综合定价方法，本年度公司定价策略未发生显著变动。2025年白酒行业在宏观经济周期、产业调整周期与政策调整的多重影响下进入深度调整阶段，商务宴请、宴席等传统消费场景恢复较缓，行业库", "stocks": "1.600779"}, {"time": "2026-07-01 23:38:43", "title": "达飞轮船（CMA CGM）表示 公司有望在2027年底前超越马士基", "summary": "【达飞轮船（CMA CGM）表示 公司有望在2027年底前超越马士基】达飞轮船（CMACGM）表示，凭借当前的船舶订单，公司有望在2027年底前超越马士基（Maersk），成为全球第二大集装箱航运公司。", "stocks": ""}, {"time": "2026-07-01 23:37:41", "title": "北汽蓝谷：子公司2026年6月销量同比增长152.54%", "summary": "【北汽蓝谷：子公司2026年6月销量同比增长152.54%】北汽蓝谷(600733.SH)公告称，公司子公司2026年6月产销快报显示，当月产量26298辆，同比增长91.31%；销量30282辆，同比增长152.54%。本年累计产量93670辆，同比增长37.73%；累计销量98895辆，同比增长47.27%。", "stocks": "1.600733"}], "count": 15}
