{"updated": "2026-06-19T22:42:10Z", "source": "hackernews-top", "data": [{"rank": 1, "id": 48600093, "title": "Norway imposes near ban on AI in elementary school", "score": 190, "author": "ilreb", "comments": 129, "url": "https://www.reuters.com/technology/norway-imposes-near-ban-ai-elementary-school-2026-06-19/"}, {"rank": 2, "id": 48599515, "title": "There are no instances in ATProto", "score": 287, "author": "danabramov", "comments": 170, "url": "https://overreacted.io/there-are-no-instances-in-atproto/"}, {"rank": 3, "id": 48600312, "title": "Hyundai buys Boston Dynamics", "score": 551, "author": "ck2", "comments": 263, "url": "https://startupfortune.com/hyundai-takes-full-control-of-boston-dynamics-as-softbank-exits-for-325-million/"}, {"rank": 4, "id": 48514843, "title": "I used sound waves to make espresso. It could cut coffee‑brewing energy use by ¾", "score": 141, "author": "zeristor", "comments": 85, "url": "https://theconversation.com/i-used-sound-waves-to-make-espresso-it-could-cut-coffee-brewing-energy-use-by-75-284929"}, {"rank": 5, "id": 48603761, "title": "The UK's New Under-16 Social Media Ban Will Cause More Harm Than It Prevents", "score": 33, "author": "Brajeshwar", "comments": 27, "url": "https://www.eff.org/deeplinks/2026/06/uks-new-under-16-social-media-ban-will-cause-more-harm-it-prevents"}, {"rank": 6, "id": 48598586, "title": "How many of the 170k English words do you know?", "score": 184, "author": "abnry", "comments": 294, "url": "https://vocabowl-870366514258.us-west1.run.app/"}, {"rank": 7, "id": 48595511, "title": "Project Valhalla, Explained: How a Decade of Work Arrives in JDK 28", "score": 523, "author": "philonoist", "comments": 321, "url": "https://www.jvm-weekly.com/p/project-valhalla-explained-how-a"}, {"rank": 8, "id": 48602817, "title": "Think of the Children: How to Force Real ID for All Internet Traffic (2023)", "score": 10, "author": "Bender", "comments": 0, "url": "https://nochan.net/b/Internet-Crap/20230829-Think-Of-The-Children/"}, {"rank": 9, "id": 48602918, "title": "Surprising Economics of Load-Balanced Systems", "score": 8, "author": "KraftyOne", "comments": 0, "url": "https://brooker.co.za/blog/2020/08/06/erlang.html"}, {"rank": 10, "id": 48602352, "title": "Bobby Prince, composer for Doom, Wolfenstein 3D, and Duke Nukem 3D, has died", "score": 26, "author": "pgrote", "comments": 4, "url": "https://www.legacy.com/legacy/robert-bobby-prince-lll"}, {"rank": 11, "id": 48600345, "title": "Google workspace threatening to block Firefox access", "score": 373, "author": "birdculture", "comments": 122, "url": "https://tales.fromprod.com/2026/169/google-workspace-threatening-to-block-firefox.html"}, {"rank": 12, "id": 48541777, "title": "A 1976 university experiment spun up the U.S. wind industry", "score": 54, "author": "pseudolus", "comments": 4, "url": "https://spectrum.ieee.org/william-heronemus-wind-energy"}, {"rank": 13, "id": 48553161, "title": "Telescope Ranchers", "score": 91, "author": "bookofjoe", "comments": 31, "url": "https://kottke.org/26/06/telescope-ranchers"}, {"rank": 14, "id": 48600950, "title": "A new bill takes aim at government pressure to silence lawful online speech", "score": 202, "author": "hn_acker", "comments": 106, "url": "https://www.eff.org/deeplinks/2026/06/new-bill-takes-aim-government-pressure-silence-lawful-online-speech"}, {"rank": 15, "id": 48553388, "title": "DuckDB Internals Part 1", "score": 419, "author": "marklit", "comments": 128, "url": "https://www.greybeam.ai/blog/duckdb-internals-part-1"}, {"rank": 16, "id": 48600946, "title": "Court Records Should Be Free", "score": 145, "author": "hn_acker", "comments": 26, "url": "https://www.eff.org/deeplinks/2026/06/court-records-should-be-free"}, {"rank": 17, "id": 48548612, "title": "Egyptian Fractions", "score": 31, "author": "luu", "comments": 0, "url": "https://blog.plover.com/math/egyptian-fractions.html"}, {"rank": 18, "id": 48603664, "title": "Zenzizenzizenzic", "score": 17, "author": "gyosifov", "comments": 11, "url": "https://en.wikipedia.org/wiki/Zenzizenzizenzic"}, {"rank": 19, "id": 48549118, "title": "Zen and the Art of Machine Learning Research", "score": 226, "author": "jxmorris12", "comments": 73, "url": "https://blog.jxmo.io/p/zen-and-the-art-of-machine-learning"}, {"rank": 20, "id": 48602571, "title": "Companies rein in AI usage as costs strain budgets", "score": 72, "author": "fandorin", "comments": 50, "url": "https://www.ft.com/content/1d37cc08-e0aa-45a4-a45d-4ad282529314"}], "count": 20}
