{
  "updated": "2026-06-25T10:33:55Z",
  "sources": [
    {
      "name": "eastmoney-news",
      "file": "data/eastmoney-news.json",
      "count": 15,
      "updated": "2026-06-25T10:33:21Z"
    },
    {
      "name": "hackernews",
      "file": "data/hackernews.json",
      "count": 20,
      "updated": "2026-06-25T10:32:19Z"
    },
    {
      "name": "stackoverflow",
      "file": "data/stackoverflow.json",
      "count": 15,
      "updated": "2026-06-25T10:33:53Z"
    },
    {
      "name": "wikipedia",
      "file": "data/wikipedia.json",
      "count": 15,
      "updated": "2026-06-25T10:33:55Z"
    }
  ]
}
