{"updated": "2026-07-14T01:19:12Z", "source": "wikipedia-trending", "data": [{"rank": 1, "title": "Lindsey_Graham", "description": "American politician (1955–2026)", "views": 2652838}, {"rank": 2, "title": "Jude_Bellingham", "description": "English footballer (born 2003)", "views": 818677}, {"rank": 3, "title": "Jannik_Sinner", "description": "Italian tennis player (born 2001)", "views": 781515}, {"rank": 4, "title": "Alexander_Zverev", "description": "German tennis player (born 1997)", "views": 529859}, {"rank": 5, "title": "2026_FIFA_World_Cup", "description": "Soccer tournament in North America", "views": 506910}, {"rank": 6, "title": "Erling_Haaland", "description": "Norwegian footballer (born 2000)", "views": 505741}, {"rank": 7, "title": "Conor_McGregor", "description": "Irish mixed martial artist (born 1988)", "views": 474875}, {"rank": 8, "title": "Mitch_McConnell", "description": "American politician and attorney (born 1942)", "views": 453550}, {"rank": 9, "title": "Lionel_Messi", "description": "Argentine footballer (born 1987)", "views": 370656}, {"rank": 10, "title": "UFC_329", "description": "2026 mixed martial arts event", "views": 343937}, {"rank": 11, "title": "S._Janaki", "description": "Indian singer (1938–2026)", "views": 338187}, {"rank": 12, "title": "Ann_Widdecombe", "description": "British politician and media personality (1947–2026)", "views": 288455}, {"rank": 13, "title": "Jayden_Adams", "description": "South African soccer player (2001–2026)", "views": 272119}, {"rank": 14, "title": "FIFA_Men's_World_Ranking", "description": "World ranking list", "views": 267252}, {"rank": 15, "title": "Vinod_Khosla", "description": "Indian-American businessman (born 1955)", "views": 253601}], "count": 15}
